{
  "user": [
    {
      "id": "YHjfRPVDO",
      "email": "poer611@naver.com",
      "password": "123123",
      "displayName": "혜수"
    },
    {
      "id": "fMXTe6Vlq",
      "email": "wek611@daum.net",
      "password": "121212",
      "displayName": "조혜수"
    },
    {
      "id": "2WIKiZ2nv",
      "email": "kea7077@naver.com",
      "password": "$2b$10$hZf7k6810XqsbRpwPL.NHeJl5.3aBFfZ79XSC6FsqbLQMSXh7XfKS",
      "displayName": "hs"
    },
    {
      "id": "NBi_BoA-Z",
      "email": "hs0330@naver.com",
      "password": "$2b$10$PTcLyaiO3v/NnWREq0gt8.nKsXbS2ScaYE9bQVA2yliWGp1a7hgZe",
      "displayName": "hs"
    },
    {
      "id": "8Fr330Smr",
      "email": "hs00@naver.com",
      "password": "$2b$10$KkHGir30gkuDQEEyEVvpDujo9zs7Nync5IRDd7tnh4/AdxnEfUCM2",
      "displayName": "혜수"
    }
  ]
}